<?xml version="1.0"?>
<toolbars version="1.0">
<available>
    <toolitem name="ImageOpen"/>
    <toolitem name="ImageSave"/>
    <toolitem name="ImagePrint"/>
    <toolitem name="ImageProperties"/>
    <toolitem name="ViewImageCollection"/>
    <toolitem name="ViewFullscreen"/>
    <toolitem name="ViewSlideshow"/>
    <toolitem name="ViewZoomIn"/>
    <toolitem name="ViewZoomOut"/>
    <toolitem name="ViewZoomNormal"/>
    <toolitem name="ViewZoomFit"/>
    <toolitem name="EditRotate270"/>
    <toolitem name="EditRotate90"/>
    <toolitem name="GoFirst"/>
    <toolitem name="GoLast"/>
    <toolitem name="GoPrevious"/>
    <toolitem name="GoNext"/>
    <toolitem name="EditMoveToTrash"/>
</available>
<toolbar name="Toolbar">
    <toolitem name="GoPrevious"/>
    <toolitem name="GoNext"/>
    <separator/>
    <toolitem name="ViewZoomIn"/>
    <toolitem name="ViewZoomOut"/>
    <toolitem name="ViewZoomNormal"/>
    <toolitem name="ViewZoomFit"/>
    <separator/>
    <toolitem name="EditRotate270"/>
    <toolitem name="EditRotate90"/>
 </toolbar>
</toolbars>
